GithubMaker/__init__.py
GithubMaker/make.py
GithubMaker-1.1.5.dist-info/LICENSE.md
GithubMaker-1.1.5.dist-info/METADATA
GithubMaker-1.1.5.dist-info/WHEEL
GithubMaker-1.1.5.dist-info/top_level.txt
GithubMaker-1.1.5.dist-info/RECORD
