Metadata-Version: 2.1
Name: GithubMaker
Version: 1.1.5
Summary: Creates Github related documents easily
Home-page: https://github.com/yagiziskirik/GithubMaker
Author: Yagiz Iskirik
Author-email: yagiziskirik@icloud.com
Classifier: Programming Language :: Python :: 3
Classifier: License :: OSI Approved :: MIT License
Classifier: Operating System :: OS Independent
Requires-Python: >=3.7
License-File: LICENSE.md
